[
{
    "name": "Fabio",
    "last_name": "Pagoti",
    "gender": "M",
    "vacation": true,
    "location": "building"
},
{
    "name": "Marcelo",
    "last_name": "Silva",
    "gender": "M",
    "vacation": false,
    "location": "building"
},
{
    "name": "Isabela",
    "last_name": "Nascimento",
    "gender": "F",
    "vacation": false,
    "location": "factory"
},
{
    "name": "Leonardo",
    "last_name": "Pinheiro",
    "gender": "M",
    "vacation": false,
    "location": "building"
},
{
    "name": "Paula",
    "last_name": "Assunção",
    "gender": "F",
    "vacation": true,
    "location": "factory"
},
{
    "name": "Rafael",
    "last_name": "Lima",
    "gender": "M",
    "vacation": false,
    "location": "building"
}]